.gitignore
AUTHORS
CHANGELOG.rst
CONTRIBUTING.rst
INSTALL
LICENSE
MANIFEST.in
README.md
README.rst
codecov.yml
readthedocs.yml
requirements.txt
setup.cfg
setup.py
tox.ini
.eggs/README.txt
.eggs/setuptools_scm-4.1.2-py2.7.egg/EGG-INFO/LICENSE
.eggs/setuptools_scm-4.1.2-py2.7.egg/EGG-INFO/PKG-INFO
.eggs/setuptools_scm-4.1.2-py2.7.egg/EGG-INFO/RECORD
.eggs/setuptools_scm-4.1.2-py2.7.egg/EGG-INFO/WHEEL
.eggs/setuptools_scm-4.1.2-py2.7.egg/EGG-INFO/entry_points.txt
.eggs/setuptools_scm-4.1.2-py2.7.egg/EGG-INFO/requires.txt
.eggs/setuptools_scm-4.1.2-py2.7.egg/EGG-INFO/top_level.txt
.eggs/setuptools_scm-4.1.2-py2.7.egg/EGG-INFO/zip-safe
.eggs/setuptools_scm-4.1.2-py2.7.egg/setuptools_scm/__init__.py
.eggs/setuptools_scm-4.1.2-py2.7.egg/setuptools_scm/__init__.pyc
.eggs/setuptools_scm-4.1.2-py2.7.egg/setuptools_scm/__main__.py
.eggs/setuptools_scm-4.1.2-py2.7.egg/setuptools_scm/config.py
.eggs/setuptools_scm-4.1.2-py2.7.egg/setuptools_scm/config.pyc
.eggs/setuptools_scm-4.1.2-py2.7.egg/setuptools_scm/discover.py
.eggs/setuptools_scm-4.1.2-py2.7.egg/setuptools_scm/discover.pyc
.eggs/setuptools_scm-4.1.2-py2.7.egg/setuptools_scm/file_finder.py
.eggs/setuptools_scm-4.1.2-py2.7.egg/setuptools_scm/file_finder.pyc
.eggs/setuptools_scm-4.1.2-py2.7.egg/setuptools_scm/file_finder_git.py
.eggs/setuptools_scm-4.1.2-py2.7.egg/setuptools_scm/file_finder_git.pyc
.eggs/setuptools_scm-4.1.2-py2.7.egg/setuptools_scm/file_finder_hg.py
.eggs/setuptools_scm-4.1.2-py2.7.egg/setuptools_scm/file_finder_hg.pyc
.eggs/setuptools_scm-4.1.2-py2.7.egg/setuptools_scm/git.py
.eggs/setuptools_scm-4.1.2-py2.7.egg/setuptools_scm/hacks.py
.eggs/setuptools_scm-4.1.2-py2.7.egg/setuptools_scm/hg.py
.eggs/setuptools_scm-4.1.2-py2.7.egg/setuptools_scm/integration.py
.eggs/setuptools_scm-4.1.2-py2.7.egg/setuptools_scm/integration.pyc
.eggs/setuptools_scm-4.1.2-py2.7.egg/setuptools_scm/utils.py
.eggs/setuptools_scm-4.1.2-py2.7.egg/setuptools_scm/utils.pyc
.eggs/setuptools_scm-4.1.2-py2.7.egg/setuptools_scm/version.py
.eggs/setuptools_scm-4.1.2-py2.7.egg/setuptools_scm/version.pyc
.eggs/setuptools_scm-4.1.2-py2.7.egg/setuptools_scm/win_py31_compat.py
capabilities-data/.gitignore
capabilities-data/.travis.yml
capabilities-data/LICENSE.md
capabilities-data/README.md
capabilities-data/data/encoding.yml
capabilities-data/data/profile/AF-240.yml
capabilities-data/data/profile/CT-S651.yml
capabilities-data/data/profile/NT-5890K.yml
src/escpos.egg-info/PKG-INFO
src/escpos.egg-info/SOURCES.txt
src/escpos.egg-info/dependency_links.txt
src/escpos.egg-info/entry_points.txt
src/escpos.egg-info/not-zip-safe
src/escpos.egg-info/requires.txt
src/escpos.egg-info/top_level.txt
src/python_escpos.egg-info/PKG-INFO
src/python_escpos.egg-info/SOURCES.txt
src/python_escpos.egg-info/dependency_links.txt
src/python_escpos.egg-info/entry_points.txt
src/python_escpos.egg-info/not-zip-safe
src/python_escpos.egg-info/requires.txt
src/python_escpos.egg-info/top_level.txt
