Metadata-Version: 1.2
Name: escpos
Version: 1.8
Summary: Python library to manipulate ESC/POS Printers
Home-page: http://www.bitbucket.org/presik/psk-escpos/
Author: Oscar Alvarez
Author-email: oscar.alvarez.montero@gmail.com
Maintainer: Patrick Kanzler
Maintainer-email: dev@pkanzler.de
License: LGPL
Download-URL: http://www.bitbucket.org/presik/psk-escpos/
Project-URL: Bug Tracker, https://github.com/python-escpos/python-escpos/issues
Project-URL: Documentation, https://python-escpos.readthedocs.io/en/latest/
Project-URL: Release Notes, https://github.com/python-escpos/python-escpos/releases
Keywords: ESC/POS,thermoprinter,voucher printer,printing,receipt
Platform: any
Classifier: Development Status :: 5 - Production/Stable
Classifier: Intended Audience :: Developers
Classifier: License :: OSI Approved :: GNU Library or Lesser General Public License (LGPL)
Classifier: Natural Language :: English
Classifier: Operating System :: OS Independent
Classifier: Programming Language :: Python :: 3.7
Classifier: Topic :: Printing
Classifier: Topic :: Software Development :: Libraries
Classifier: Topic :: Software Development :: Libraries :: Python Modules
Requires-Python: >=3.5
